{"swagger":"2.0","info":{"version":"1.0","title":"application"},"basePath":"pcs-gse00011861.process.us2.oraclecloud.com","paths":{"/bpm/api/4.0/":{"get":{"operationId":"","parameters":[]}},"/bpm/api/4.0//quickStartApps":{"get":{"operationId":"/quickStartApps","parameters":[]},"post":{"operationId":"/quickStartApps","consumes":["multipart/form-data","application/octet-stream","application/zip"],"parameters":[{"in":"body","name":"body","description":"Request body","required":true}]}},"/bpm/api/4.0//quickStartApps/{quickStartAppId}":{"get":{"operationId":"{quickStartAppId}","parameters":[{"name":"quickStartAppId","in":"path","required":true,"type":"string"}]},"delete":{"operationId":"{quickStartAppId}","parameters":[{"name":"quickStartAppId","in":"path","required":true,"type":"string"}]}},"/bpm/api/4.0//recentProjects":{"get":{"operationId":"/recentProjects","parameters":[]}},"/bpm/api/4.0//spaces":{"get":{"operationId":"/spaces","parameters":[{"name":"expand","in":"query","required":false,"type":"string"},{"name":"expand","in":"query","required":false,"type":"string"}]},"post":{"operationId":"/spaces","consumes":["application/x-www-form-urlencoded"],"parameters":[{"in":"body","name":"body","description":"Request body","required":true}]}},"/bpm/api/4.0//spaces/{spaceId}":{"get":{"operationId":"{spaceId}","parameters":[{"name":"expand","in":"query","required":false,"type":"string"},{"name":"spaceId","in":"path","required":true,"type":"string"},{"name":"expand","in":"query","required":false,"type":"string"}]},"delete":{"operationId":"{spaceId}","parameters":[{"name":"spaceId","in":"path","required":true,"type":"string"}]}},"/bpm/api/4.0//spaces/{spaceId}/permissions":{"get":{"operationId":"/spaces/{spaceId}/permissions","parameters":[{"name":"spaceId","in":"path","required":true,"type":"string"}]}},"/bpm/api/4.0//spaces/{spaceId}/permissions/{principal}":{"get":{"operationId":"{principal}","parameters":[{"name":"spaceId","in":"path","required":true,"type":"string"},{"name":"principal","in":"path","required":true,"type":"string"}]},"put":{"operationId":"{principal}","consumes":["application/x-www-form-urlencoded"],"parameters":[{"name":"spaceId","in":"path","required":true,"type":"string"},{"name":"principal","in":"path","required":true,"type":"string"},{"in":"body","name":"body","description":"Request body","required":true}]},"delete":{"operationId":"{principal}","parameters":[{"name":"spaceId","in":"path","required":true,"type":"string"},{"name":"principal","in":"path","required":true,"type":"string"}]}},"/bpm/api/4.0//spaces/{spaceId}/projects":{"get":{"operationId":"/spaces/{spaceId}/projects","parameters":[{"name":"expand","in":"query","required":false,"type":"string"},{"name":"spaceId","in":"path","required":true,"type":"string"},{"name":"expand","in":"query","required":false,"type":"string"}]},"post":{"operationId":"/spaces/{spaceId}/projects","consumes":["multipart/form-data","application/octet-stream","application/zip"],"parameters":[{"name":"spaceId","in":"path","required":true,"type":"string"},{"in":"body","name":"body","description":"Request body","required":true}]}},"/bpm/api/4.0//spaces/{spaceId}/projects/{projectId}":{"get":{"operationId":"{projectId}","parameters":[{"name":"expand","in":"query","required":false,"type":"string"},{"name":"spaceId","in":"path","required":true,"type":"string"},{"name":"projectId","in":"path","required":true,"type":"string"},{"name":"expand","in":"query","required":false,"type":"string"}]},"put":{"operationId":"{projectId}","consumes":["application/x-www-form-urlencoded"],"parameters":[{"name":"spaceId","in":"path","required":true,"type":"string"},{"name":"projectId","in":"path","required":true,"type":"string"},{"in":"body","name":"body","description":"Request body","required":true}]},"delete":{"operationId":"{projectId}","parameters":[{"name":"spaceId","in":"path","required":true,"type":"string"},{"name":"projectId","in":"path","required":true,"type":"string"}]}},"/bpm/api/4.0//spaces/{spaceId}/projects/{projectId}/clone":{"post":{"operationId":"{projectId}/clone","consumes":["application/json"],"parameters":[{"name":"spaceId","in":"path","required":true,"type":"string"},{"name":"projectId","in":"path","required":true,"type":"string"},{"in":"body","name":"body","description":"Request body","required":true}]}},"/bpm/api/4.0//spaces/{spaceId}/projects/{projectId}/deploy":{"post":{"operationId":"{projectId}/deploy","consumes":["application/json"],"parameters":[{"name":"targetId","in":"query","required":false,"type":"string"},{"name":"spaceId","in":"path","required":true,"type":"string"},{"name":"projectId","in":"path","required":true,"type":"string"},{"name":"targetId","in":"query","required":false,"type":"string"},{"in":"body","name":"body","description":"Request body","required":true}]}},"/bpm/api/4.0//spaces/{spaceId}/projects/{projectId}/exp":{"get":{"operationId":"{projectId}/exp","parameters":[{"name":"spaceId","in":"path","required":true,"type":"string"},{"name":"projectId","in":"path","required":true,"type":"string"}]}},"/bpm/api/4.0//spaces/{spaceId}/projects/{projectId}/processes":{"get":{"operationId":"/spaces/{spaceId}/projects/{projectId}/processes","parameters":[{"name":"projectId","in":"path","required":true,"type":"string"},{"name":"spaceId","in":"path","required":true,"type":"string"}]},"post":{"operationId":"/spaces/{spaceId}/projects/{projectId}/processes","consumes":["application/json"],"parameters":[{"name":"projectId","in":"path","required":true,"type":"string"},{"name":"spaceId","in":"path","required":true,"type":"string"},{"in":"body","name":"body","description":"Request body","required":true}]}},"/bpm/api/4.0//spaces/{spaceId}/projects/{projectId}/processes/{processId}":{"get":{"operationId":"{processId}","parameters":[{"name":"projectId","in":"path","required":true,"type":"string"},{"name":"spaceId","in":"path","required":true,"type":"string"},{"name":"processId","in":"path","required":true,"type":"string"}]},"delete":{"operationId":"{processId}","parameters":[{"name":"projectId","in":"path","required":true,"type":"string"},{"name":"spaceId","in":"path","required":true,"type":"string"},{"name":"processId","in":"path","required":true,"type":"string"}]}},"/bpm/api/4.0//spaces/{spaceId}/projects/{projectId}/snapshots":{"get":{"operationId":"/spaces/{spaceId}/projects/{projectId}/snapshots","parameters":[{"name":"projectId","in":"path","required":true,"type":"string"},{"name":"spaceId","in":"path","required":true,"type":"string"}]},"post":{"operationId":"/spaces/{spaceId}/projects/{projectId}/snapshots","consumes":["application/x-www-form-urlencoded"],"parameters":[{"name":"projectId","in":"path","required":true,"type":"string"},{"name":"spaceId","in":"path","required":true,"type":"string"},{"in":"body","name":"body","description":"Request body","required":true}]}},"/bpm/api/4.0//spaces/{spaceId}/projects/{projectId}/snapshots/{snapshotId}":{"get":{"operationId":"{snapshotId}","parameters":[{"name":"projectId","in":"path","required":true,"type":"string"},{"name":"spaceId","in":"path","required":true,"type":"string"},{"name":"snapshotId","in":"path","required":true,"type":"string"}]},"delete":{"operationId":"{snapshotId}","parameters":[{"name":"projectId","in":"path","required":true,"type":"string"},{"name":"spaceId","in":"path","required":true,"type":"string"},{"name":"snapshotId","in":"path","required":true,"type":"string"}]}},"/bpm/api/4.0//spaces/{spaceId}/projects/{projectId}/snapshots/{snapshotId}/deploy":{"post":{"operationId":"{snapshotId}/deploy","consumes":["application/json"],"parameters":[{"name":"targetId","in":"query","required":false,"type":"string"},{"name":"projectId","in":"path","required":true,"type":"string"},{"name":"spaceId","in":"path","required":true,"type":"string"},{"name":"snapshotId","in":"path","required":true,"type":"string"},{"name":"targetId","in":"query","required":false,"type":"string"},{"in":"body","name":"body","description":"Request body","required":true}]}},"/bpm/api/4.0//spaces/{spaceId}/projects/{projectId}/snapshots/{snapshotId}/exp":{"get":{"operationId":"{snapshotId}/exp","parameters":[{"name":"projectId","in":"path","required":true,"type":"string"},{"name":"spaceId","in":"path","required":true,"type":"string"},{"name":"snapshotId","in":"path","required":true,"type":"string"}]}},"/bpm/api/4.0//targets":{},"/bpm/api/4.0//targets/{targetId}/projects/{projectId}/revisions":{"get":{"operationId":"{targetId}/projects/{projectId}/revisions","parameters":[{"name":"Authorization","in":"header","required":false,"type":"string"},{"name":"targetId","in":"path","required":true,"type":"string"},{"name":"projectId","in":"path","required":true,"type":"string"},{"name":"Authorization","in":"header","required":false,"type":"string"}]}},"/bpm/api/4.0//targets/{targetId}/projects/{projectId}/revisions/{revision}":{"get":{"operationId":"{targetId}/projects/{projectId}/revisions/{revision}","parameters":[{"name":"Authorization","in":"header","required":false,"type":"string"},{"name":"revision","in":"path","required":true,"type":"string"},{"name":"targetId","in":"path","required":true,"type":"string"},{"name":"projectId","in":"path","required":true,"type":"string"},{"name":"Authorization","in":"header","required":false,"type":"string"}]},"delete":{"operationId":"{targetId}/projects/{projectId}/revisions/{revision}","parameters":[{"name":"revision","in":"path","required":true,"type":"string"},{"name":"targetId","in":"path","required":true,"type":"string"},{"name":"projectId","in":"path","required":true,"type":"string"}]},"patch":{"operationId":"{targetId}/projects/{projectId}/revisions/{revision}","consumes":["application/json"],"parameters":[{"name":"revision","in":"path","required":true,"type":"string"},{"name":"targetId","in":"path","required":true,"type":"string"},{"name":"projectId","in":"path","required":true,"type":"string"}]}},"/bpm/api/4.0/analyticsdataobjects":{"get":{"operationId":"analyticsdataobjects","parameters":[{"name":"applicationName","in":"query","required":false,"type":"string"},{"name":"applicationName","in":"query","required":false,"type":"string"}]}},"/bpm/api/4.0/analyticsdataobjects/{dataObjectName}":{"get":{"operationId":"{dataObjectName}","parameters":[{"name":"dataObjectName","in":"path","required":true,"type":"string"}]}},"/bpm/api/4.0/analyticsdataobjects/{dataObjectName}/data":{"get":{"operationId":"{dataObjectName}/data","parameters":[{"name":"offset","in":"query","required":false,"type":"int"},{"name":"limit","in":"query","required":false,"type":"int"},{"name":"since","in":"query","required":false,"type":"string"},{"name":"totalResults","in":"query","required":false,"type":"boolean"},{"name":"dataObjectName","in":"path","required":true,"type":"string"},{"name":"offset","in":"query","required":false,"type":"int"},{"name":"limit","in":"query","required":false,"type":"int"},{"name":"since","in":"query","required":false,"type":"string"},{"name":"totalResults","in":"query","required":false,"type":"boolean"}]}},"/bpm/api/4.0/analyticsqueries":{"get":{"operationId":"analyticsqueries","parameters":[{"name":"queryType","in":"query","required":false,"type":"string"},{"name":"queryType","in":"query","required":false,"type":"string"}]},"post":{"operationId":"analyticsqueries","consumes":["application/json"],"parameters":[{"name":"action","in":"query","required":false,"type":"string"},{"name":"action","in":"query","required":false,"type":"string"},{"in":"body","name":"body","description":"Request body","required":true}]}},"/bpm/api/4.0/analyticsqueries-aggregateoperations":{"get":{"operationId":"analyticsqueries-aggregateoperations","parameters":[]}},"/bpm/api/4.0/analyticsqueries-comparisonoperators":{"get":{"operationId":"analyticsqueries-comparisonoperators","parameters":[{"name":"columnDataType","in":"query","required":false,"type":"string"},{"name":"columnDataType","in":"query","required":false,"type":"string"}]}},"/bpm/api/4.0/analyticsqueries-datasources":{"get":{"operationId":"analyticsqueries-datasources","parameters":[]}},"/bpm/api/4.0/analyticsqueries-datasources/{dataSource}":{"get":{"operationId":"{dataSource}","parameters":[{"name":"dataSource","in":"path","required":true,"type":"string"}]}},"/bpm/api/4.0/analyticsqueries-datasources/{dataSource}/columns":{"get":{"operationId":"{dataSource}/columns","parameters":[{"name":"applicationName","in":"query","required":false,"type":"string"},{"name":"dataSource","in":"path","required":true,"type":"string"},{"name":"applicationName","in":"query","required":false,"type":"string"}]}},"/bpm/api/4.0/analyticsqueries/{businessQueryId}":{"get":{"operationId":"{businessQueryId}","parameters":[{"name":"processNames","in":"query","required":false,"type":"string"},{"name":"assigneeType","in":"query","required":false,"type":"string"},{"name":"topN","in":"query","required":false,"type":"int"},{"name":"since","in":"query","required":false,"type":"int"},{"name":"applicationName","in":"query","required":false,"type":"string"},{"name":"action","in":"query","required":false,"type":"string"},{"name":"businessQueryId","in":"path","required":true,"type":"string"},{"name":"processNames","in":"query","required":false,"type":"string"},{"name":"assigneeType","in":"query","required":false,"type":"string"},{"name":"topN","in":"query","required":false,"type":"int"},{"name":"since","in":"query","required":false,"type":"int"},{"name":"applicationName","in":"query","required":false,"type":"string"},{"name":"action","in":"query","required":false,"type":"string"}]},"put":{"operationId":"{businessQueryId}","consumes":["application/json"],"parameters":[{"name":"businessQueryId","in":"path","required":true,"type":"string"},{"in":"body","name":"body","description":"Request body","required":true}]},"delete":{"operationId":"{businessQueryId}","parameters":[{"name":"businessQueryId","in":"path","required":true,"type":"string"}]}},"/bpm/api/4.0/archiverequests":{"get":{"operationId":"archiverequests","parameters":[{"name":"limit","in":"query","required":false,"type":"int"},{"name":"offset","in":"query","required":false,"type":"int"},{"name":"totalResults","in":"query","required":false,"type":"boolean"},{"name":"type","in":"query","required":false,"type":"string"},{"name":"limit","in":"query","required":false,"type":"int"},{"name":"offset","in":"query","required":false,"type":"int"},{"name":"totalResults","in":"query","required":false,"type":"boolean"},{"name":"type","in":"query","required":false,"type":"string"}]},"post":{"operationId":"archiverequests","consumes":["application/json"],"parameters":[{"in":"body","name":"body","description":"Request body","required":true}]}},"/bpm/api/4.0/archiverequests/{id}":{"get":{"operationId":"{id}","parameters":[{"name":"id","in":"path","required":true,"type":"string"}]}},"/bpm/api/4.0/archives":{"get":{"operationId":"archives","parameters":[{"name":"type","in":"query","required":false,"type":"string"},{"name":"startDateFilter","in":"query","required":false,"type":"string"},{"name":"endDateFilter","in":"query","required":false,"type":"string"},{"name":"type","in":"query","required":false,"type":"string"},{"name":"startDateFilter","in":"query","required":false,"type":"string"},{"name":"endDateFilter","in":"query","required":false,"type":"string"}]}},"/bpm/api/4.0/archives/{id}":{"get":{"operationId":"{id}","parameters":[{"name":"id","in":"path","required":true,"type":"string"}]}},"/bpm/api/4.0/identities":{"get":{"operationId":"identities","parameters":[{"name":"searchPattern","in":"query","required":false,"type":"string"},{"name":"scope","in":"query","required":false,"type":"string"},{"name":"firstname","in":"query","required":false,"type":"string"},{"name":"lastname","in":"query","required":false,"type":"string"},{"name":"email","in":"query","required":false,"type":"string"},{"name":"limit","in":"query","required":false,"type":"int"},{"name":"offset","in":"query","required":false,"type":"int"},{"name":"totalResults","in":"query","required":false,"type":"boolean"},{"name":"searchPattern","in":"query","required":false,"type":"string"},{"name":"scope","in":"query","required":false,"type":"string"},{"name":"firstname","in":"query","required":false,"type":"string"},{"name":"lastname","in":"query","required":false,"type":"string"},{"name":"email","in":"query","required":false,"type":"string"},{"name":"limit","in":"query","required":false,"type":"int"},{"name":"offset","in":"query","required":false,"type":"int"},{"name":"totalResults","in":"query","required":false,"type":"boolean"}]}},"/bpm/api/4.0/identities/groups/{groupid}":{"get":{"operationId":"groups/{groupid}","parameters":[{"name":"groupid","in":"path","required":true,"type":"string"}]}},"/bpm/api/4.0/identities/groups/{groupid}/users":{"get":{"operationId":"groups/{groupid}/users","parameters":[{"name":"totalResults","in":"query","required":false,"type":"boolean"},{"name":"groupid","in":"path","required":true,"type":"string"},{"name":"totalResults","in":"query","required":false,"type":"boolean"}]}},"/bpm/api/4.0/identities/loggedInUser":{"get":{"operationId":"loggedInUser","parameters":[]}},"/bpm/api/4.0/identities/roles/{roleid}":{"get":{"operationId":"roles/{roleid}","parameters":[{"name":"roleid","in":"path","required":true,"type":"string"}]}},"/bpm/api/4.0/identities/users/{userid}":{"get":{"operationId":"users/{userid}","parameters":[{"name":"includeGrantedRolesFlag","in":"query","required":false,"type":"boolean"},{"name":"includeAssignedGroupsFlag","in":"query","required":false,"type":"boolean"},{"name":"userid","in":"path","required":true,"type":"string"},{"name":"includeGrantedRolesFlag","in":"query","required":false,"type":"boolean"},{"name":"includeAssignedGroupsFlag","in":"query","required":false,"type":"boolean"}]}},"/bpm/api/4.0/identities/{scope}":{"get":{"operationId":"{scope}","parameters":[{"name":"totalResults","in":"query","required":false,"type":"boolean"},{"name":"scope","in":"path","required":true,"type":"string"},{"name":"totalResults","in":"query","required":false,"type":"boolean"}]}},"/bpm/api/4.0/metadata-catalog":{"get":{"operationId":"metadata-catalog","parameters":[]}},"/bpm/api/4.0/metadata-catalog/{resourceName}":{"get":{"operationId":"metadata-catalog/{resourceName}","parameters":[{"name":"resourceName","in":"path","required":true,"type":"string"}]}},"/bpm/api/4.0/metadata-catalog/{serviceName}":{"get":{"operationId":"metadata-catalog/{serviceName}","parameters":[{"name":"serviceName","in":"path","required":true,"type":"string"}]}},"/bpm/api/4.0/process-definitions":{"get":{"operationId":"process-definitions","parameters":[{"name":"interfaceFilter","in":"query","required":false,"type":"string"},{"name":"showProcessInstancesCount","in":"query","required":false,"type":"string"},{"name":"interfaceFilter","in":"query","required":false,"type":"string"},{"name":"showProcessInstancesCount","in":"query","required":false,"type":"string"}]}},"/bpm/api/4.0/process-definitions/{processDefId}/conversations":{"get":{"operationId":"{processDefId}/conversations","parameters":[{"name":"name","in":"query","required":false,"type":"string"},{"name":"processDefId","in":"path","required":true,"type":"string"},{"name":"name","in":"query","required":false,"type":"string"}]}},"/bpm/api/4.0/process-definitions/{processDefId}/conversations/{conversationName}":{"get":{"operationId":"{processDefId}/conversations/{conversationName}","parameters":[{"name":"conversationName","in":"path","required":true,"type":"string"},{"name":"processDefId","in":"path","required":true,"type":"string"}]}},"/bpm/api/4.0/process-definitions/{processDefId}/documents":{"get":{"operationId":"{processDefId}/documents","parameters":[{"name":"expanded","in":"query","required":false,"type":"string"},{"name":"processDefId","in":"path","required":true,"type":"string"},{"name":"expanded","in":"query","required":false,"type":"string"}]}},"/bpm/api/4.0/process-definitions/{processDefId}/documents/incoming-documents":{"get":{"operationId":"{processDefId}/documents/incoming-documents","parameters":[{"name":"name","in":"query","required":false,"type":"string"},{"name":"processDefId","in":"path","required":true,"type":"string"},{"name":"name","in":"query","required":false,"type":"string"}]}},"/bpm/api/4.0/process-definitions/{processDefId}/documents/incoming-documents/{documentName}":{"get":{"operationId":"{processDefId}/documents/incoming-documents/{documentName}","parameters":[{"name":"processDefId","in":"path","required":true,"type":"string"},{"name":"documentName","in":"path","required":true,"type":"string"}]}},"/bpm/api/4.0/process-definitions/{processDefId}/documents/incoming-folders":{"get":{"operationId":"{processDefId}/documents/incoming-folders","parameters":[{"name":"name","in":"query","required":false,"type":"string"},{"name":"processDefId","in":"path","required":true,"type":"string"},{"name":"name","in":"query","required":false,"type":"string"}]}},"/bpm/api/4.0/process-definitions/{processDefId}/documents/incoming-folders/{folderName}":{"get":{"operationId":"{processDefId}/documents/incoming-folders/{folderName}","parameters":[{"name":"folderName","in":"path","required":true,"type":"string"},{"name":"processDefId","in":"path","required":true,"type":"string"}]}},"/bpm/api/4.0/process-definitions/{processDefId}/documents/managed-folders":{"get":{"operationId":"{processDefId}/documents/managed-folders","parameters":[{"name":"name","in":"query","required":false,"type":"string"},{"name":"startupFlag","in":"query","required":false,"type":"boolean"},{"name":"processDefId","in":"path","required":true,"type":"string"},{"name":"name","in":"query","required":false,"type":"string"},{"name":"startupFlag","in":"query","required":false,"type":"boolean"}]}},"/bpm/api/4.0/process-definitions/{processDefId}/documents/managed-folders/{folderName}":{"get":{"operationId":"{processDefId}/documents/managed-folders/{folderName}","parameters":[{"name":"folderName","in":"path","required":true,"type":"string"},{"name":"processDefId","in":"path","required":true,"type":"string"}]}},"/bpm/api/4.0/process-definitions/{processDefId}/startFolderName":{"get":{"operationId":"{processDefId}/startFolderName","parameters":[{"name":"processDefId","in":"path","required":true,"type":"string"}]}},"/bpm/api/4.0/process-definitions/{processDefId}/{serviceName}/form":{"get":{"operationId":"{processDefId}/{serviceName}/form","parameters":[{"name":"operation","in":"query","required":false,"type":"string"},{"name":"includeAttachments","in":"query","required":false,"type":"boolean"},{"name":"processDefId","in":"path","required":true,"type":"string"},{"name":"serviceName","in":"path","required":true,"type":"string"},{"name":"operation","in":"query","required":false,"type":"string"},{"name":"includeAttachments","in":"query","required":false,"type":"boolean"}]}},"/bpm/api/4.0/process-definitions/{processDefId}/{serviceName}/form/payload":{"get":{"operationId":"{processDefId}/{serviceName}/form/payload","parameters":[{"name":"formInstanceURL","in":"query","required":false,"type":"string"},{"name":"operation","in":"query","required":false,"type":"string"},{"name":"processDefId","in":"path","required":true,"type":"string"},{"name":"serviceName","in":"path","required":true,"type":"string"},{"name":"formInstanceURL","in":"query","required":false,"type":"string"},{"name":"operation","in":"query","required":false,"type":"string"}]}},"/bpm/api/4.0/process-definitions/{processDefId}/{serviceName}/oracleform":{"get":{"operationId":"{processDefId}/{serviceName}/oracleform","parameters":[{"name":"operation","in":"query","required":false,"type":"string"},{"name":"processDefId","in":"path","required":true,"type":"string"},{"name":"serviceName","in":"path","required":true,"type":"string"},{"name":"operation","in":"query","required":false,"type":"string"}]}},"/bpm/api/4.0/process-definitions/{processDefId}/{serviceName}/webform":{"get":{"operationId":"{processDefId}/{serviceName}/webform","parameters":[{"name":"operation","in":"query","required":false,"type":"string"},{"name":"includeAttachments","in":"query","required":false,"type":"boolean"},{"name":"processDefId","in":"path","required":true,"type":"string"},{"name":"serviceName","in":"path","required":true,"type":"string"},{"name":"operation","in":"query","required":false,"type":"string"},{"name":"includeAttachments","in":"query","required":false,"type":"boolean"}]}},"/bpm/api/4.0/processes":{"get":{"operationId":"processes","parameters":[{"name":"view","in":"query","required":false,"type":"string"},{"name":"processDefId","in":"query","required":false,"type":"string"},{"name":"processName","in":"query","required":false,"type":"string"},{"name":"priority","in":"query","required":false,"type":"string"},{"name":"processOwner","in":"query","required":false,"type":"string"},{"name":"processCreator","in":"query","required":false,"type":"string"},{"name":"processState","in":"query","required":false,"type":"string"},{"name":"assignmentFilter","in":"query","required":false,"type":"string"},{"name":"dueDateFrom","in":"query","required":false,"type":"string"},{"name":"dueDateTo","in":"query","required":false,"type":"string"},{"name":"limit","in":"query","required":false,"type":"int"},{"name":"offset","in":"query","required":false,"type":"int"},{"name":"orderBy","in":"query","required":false,"type":"string"},{"name":"totalResults","in":"query","required":false,"type":"boolean"},{"name":"since","in":"query","required":false,"type":"string"},{"name":"until","in":"query","required":false,"type":"string"},{"name":"view","in":"query","required":false,"type":"string"},{"name":"processDefId","in":"query","required":false,"type":"string"},{"name":"processName","in":"query","required":false,"type":"string"},{"name":"priority","in":"query","required":false,"type":"string"},{"name":"processOwner","in":"query","required":false,"type":"string"},{"name":"processCreator","in":"query","required":false,"type":"string"},{"name":"processState","in":"query","required":false,"type":"string"},{"name":"assignmentFilter","in":"query","required":false,"type":"string"},{"name":"dueDateFrom","in":"query","required":false,"type":"string"},{"name":"dueDateTo","in":"query","required":false,"type":"string"},{"name":"limit","in":"query","required":false,"type":"int"},{"name":"offset","in":"query","required":false,"type":"int"},{"name":"orderBy","in":"query","required":false,"type":"string"},{"name":"totalResults","in":"query","required":false,"type":"boolean"},{"name":"since","in":"query","required":false,"type":"string"},{"name":"until","in":"query","required":false,"type":"string"}]},"post":{"operationId":"processes","consumes":["multipart/mixed"],"parameters":[{"name":"processDefId","in":"query","required":false,"type":"string"},{"name":"serviceName","in":"query","required":false,"type":"string"},{"name":"operation","in":"query","required":false,"type":"string"},{"name":"action","in":"query","required":false,"type":"string"},{"name":"processDefId","in":"query","required":false,"type":"string"},{"name":"serviceName","in":"query","required":false,"type":"string"},{"name":"operation","in":"query","required":false,"type":"string"},{"name":"action","in":"query","required":false,"type":"string"},{"in":"body","name":"body","description":"Request body","required":true}]},"put":{"operationId":"processes","consumes":["*/*"],"parameters":[{"in":"body","name":"body","description":"Request body","required":true}]}},"/bpm/api/4.0/processes/{processId}":{"get":{"operationId":"{processId}","parameters":[{"name":"isProcessNumberFlag","in":"query","required":false,"type":"boolean"},{"name":"processId","in":"path","required":true,"type":"string"},{"name":"isProcessNumberFlag","in":"query","required":false,"type":"boolean"}]},"put":{"operationId":"{processId}","consumes":["application/json"],"parameters":[{"name":"processId","in":"path","required":true,"type":"string"},{"in":"body","name":"body","description":"Request body","required":true}]}},"/bpm/api/4.0/processes/{processId}/attachments":{"get":{"operationId":"{processId}/attachments","parameters":[{"name":"processId","in":"path","required":true,"type":"string"}]},"post":{"operationId":"{processId}/attachments","consumes":["multipart/mixed"],"parameters":[{"name":"processId","in":"path","required":true,"type":"string"},{"in":"body","name":"body","description":"Request body","required":true}]}},"/bpm/api/4.0/processes/{processId}/attachments/{attachmentId}":{"delete":{"operationId":"{processId}/attachments/{attachmentId}","parameters":[{"name":"attachmentId","in":"path","required":true,"type":"string"},{"name":"processId","in":"path","required":true,"type":"string"}]}},"/bpm/api/4.0/processes/{processId}/audit":{"get":{"operationId":"{processId}/audit","parameters":[{"name":"graphicFlag","in":"query","required":false,"type":"boolean"},{"name":"filterActivitiesBy","in":"query","required":false,"type":"string"},{"name":"includeFutureTasksFlag","in":"query","required":false,"type":"boolean"},{"name":"currentTaskNumber","in":"query","required":false,"type":"string"},{"name":"processId","in":"path","required":true,"type":"string"},{"name":"graphicFlag","in":"query","required":false,"type":"boolean"},{"name":"filterActivitiesBy","in":"query","required":false,"type":"string"},{"name":"includeFutureTasksFlag","in":"query","required":false,"type":"boolean"},{"name":"currentTaskNumber","in":"query","required":false,"type":"string"}]}},"/bpm/api/4.0/processes/{processId}/comments":{"get":{"operationId":"{processId}/comments","parameters":[{"name":"processId","in":"path","required":true,"type":"string"}]},"post":{"operationId":"{processId}/comments","consumes":["application/json"],"parameters":[{"name":"processId","in":"path","required":true,"type":"string"},{"in":"body","name":"body","description":"Request body","required":true}]}},"/bpm/api/4.0/processes/{processId}/conversations":{"get":{"operationId":"{processId}/conversations","parameters":[{"name":"name","in":"query","required":false,"type":"string"},{"name":"processId","in":"path","required":true,"type":"string"},{"name":"name","in":"query","required":false,"type":"string"}]}},"/bpm/api/4.0/processes/{processId}/conversations/{conversationId}":{"get":{"operationId":"{processId}/conversations/{conversationId}","parameters":[{"name":"processId","in":"path","required":true,"type":"string"},{"name":"conversationId","in":"path","required":true,"type":"string"}]}},"/bpm/api/4.0/processes/{processId}/faults":{"get":{"operationId":"{processId}/faults","parameters":[{"name":"processId","in":"path","required":true,"type":"string"}]}},"/bpm/api/4.0/processes/{processId}/folders":{"get":{"operationId":"{processId}/folders","parameters":[{"name":"name","in":"query","required":false,"type":"string"},{"name":"processId","in":"path","required":true,"type":"string"},{"name":"name","in":"query","required":false,"type":"string"}]}},"/bpm/api/4.0/processes/{processId}/folders/{folderId}":{"get":{"operationId":"{processId}/folders/{folderId}","parameters":[{"name":"processId","in":"path","required":true,"type":"string"},{"name":"folderId","in":"path","required":true,"type":"string"}]}},"/bpm/api/4.0/runtime":{"get":{"operationId":"runtime","parameters":[]}},"/bpm/api/4.0/runtime/config":{"get":{"operationId":"config","parameters":[]}},"/bpm/api/4.0/tasks":{"get":{"operationId":"tasks","parameters":[{"name":"status","in":"query","required":false,"type":"string"},{"name":"priority","in":"query","required":false,"type":"string"},{"name":"dueDateFrom","in":"query","required":false,"type":"string"},{"name":"dueDateTo","in":"query","required":false,"type":"string"},{"name":"assignment","in":"query","required":false,"type":"string"},{"name":"keyword","in":"query","required":false,"type":"string"},{"name":"fromuser","in":"query","required":false,"type":"string"},{"name":"process","in":"query","required":false,"type":"string"},{"name":"limit","in":"query","required":false,"type":"int"},{"name":"offset","in":"query","required":false,"type":"int"},{"name":"orderBy","in":"query","required":false,"type":"string"},{"name":"fields","in":"query","required":false,"type":"string"},{"name":"pattern","in":"query","required":false,"type":"string"},{"name":"showActionFlag","in":"query","required":false,"type":"boolean"},{"name":"showPermissionFlag","in":"query","required":false,"type":"boolean"},{"name":"metadataFlag","in":"query","required":false,"type":"boolean"},{"name":"totalResults","in":"query","required":false,"type":"boolean"},{"name":"since","in":"query","required":false,"type":"string"},{"name":"until","in":"query","required":false,"type":"string"},{"name":"processDefId","in":"query","required":false,"type":"string"},{"name":"instanceId","in":"query","required":false,"type":"string"},{"name":"status","in":"query","required":false,"type":"string"},{"name":"priority","in":"query","required":false,"type":"string"},{"name":"dueDateFrom","in":"query","required":false,"type":"string"},{"name":"dueDateTo","in":"query","required":false,"type":"string"},{"name":"assignment","in":"query","required":false,"type":"string"},{"name":"keyword","in":"query","required":false,"type":"string"},{"name":"fromuser","in":"query","required":false,"type":"string"},{"name":"process","in":"query","required":false,"type":"string"},{"name":"limit","in":"query","required":false,"type":"int"},{"name":"offset","in":"query","required":false,"type":"int"},{"name":"orderBy","in":"query","required":false,"type":"string"},{"name":"fields","in":"query","required":false,"type":"string"},{"name":"pattern","in":"query","required":false,"type":"string"},{"name":"showActionFlag","in":"query","required":false,"type":"boolean"},{"name":"showPermissionFlag","in":"query","required":false,"type":"boolean"},{"name":"metadataFlag","in":"query","required":false,"type":"boolean"},{"name":"totalResults","in":"query","required":false,"type":"boolean"},{"name":"since","in":"query","required":false,"type":"string"},{"name":"until","in":"query","required":false,"type":"string"},{"name":"processDefId","in":"query","required":false,"type":"string"},{"name":"instanceId","in":"query","required":false,"type":"string"}]},"post":{"operationId":"tasks","consumes":["application/json"],"parameters":[{"in":"body","name":"body","description":"Request body","required":true}]},"put":{"operationId":"tasks","consumes":["application/json"],"parameters":[{"in":"body","name":"body","description":"Request body","required":true}]}},"/bpm/api/4.0/tasks/todoTask":{"post":{"operationId":"todoTask","consumes":["application/json"],"parameters":[{"in":"body","name":"body","description":"Request body","required":true}]}},"/bpm/api/4.0/tasks/views":{"get":{"operationId":"views","parameters":[]}},"/bpm/api/4.0/tasks/views/{viewname}":{"get":{"operationId":"views/{viewname}","parameters":[{"name":"status","in":"query","required":false,"type":"string"},{"name":"priority","in":"query","required":false,"type":"string"},{"name":"fromuser","in":"query","required":false,"type":"string"},{"name":"process","in":"query","required":false,"type":"string"},{"name":"dueDateFrom","in":"query","required":false,"type":"string"},{"name":"dueDateTo","in":"query","required":false,"type":"string"},{"name":"assignment","in":"query","required":false,"type":"string"},{"name":"keyword","in":"query","required":false,"type":"string"},{"name":"limit","in":"query","required":false,"type":"int"},{"name":"offset","in":"query","required":false,"type":"int"},{"name":"groupBy","in":"query","required":false,"type":"string"},{"name":"pattern","in":"query","required":false,"type":"string"},{"name":"action","in":"query","required":false,"type":"boolean"},{"name":"showPermission","in":"query","required":false,"type":"boolean"},{"name":"metadataFlag","in":"query","required":false,"type":"boolean"},{"name":"totalResults","in":"query","required":false,"type":"boolean"},{"name":"since","in":"query","required":false,"type":"string"},{"name":"until","in":"query","required":false,"type":"string"},{"name":"processDefId","in":"query","required":false,"type":"string"},{"name":"instanceId","in":"query","required":false,"type":"string"},{"name":"viewname","in":"path","required":true,"type":"string"},{"name":"status","in":"query","required":false,"type":"string"},{"name":"priority","in":"query","required":false,"type":"string"},{"name":"fromuser","in":"query","required":false,"type":"string"},{"name":"process","in":"query","required":false,"type":"string"},{"name":"dueDateFrom","in":"query","required":false,"type":"string"},{"name":"dueDateTo","in":"query","required":false,"type":"string"},{"name":"assignment","in":"query","required":false,"type":"string"},{"name":"keyword","in":"query","required":false,"type":"string"},{"name":"limit","in":"query","required":false,"type":"int"},{"name":"offset","in":"query","required":false,"type":"int"},{"name":"groupBy","in":"query","required":false,"type":"string"},{"name":"pattern","in":"query","required":false,"type":"string"},{"name":"action","in":"query","required":false,"type":"boolean"},{"name":"showPermission","in":"query","required":false,"type":"boolean"},{"name":"metadataFlag","in":"query","required":false,"type":"boolean"},{"name":"totalResults","in":"query","required":false,"type":"boolean"},{"name":"since","in":"query","required":false,"type":"string"},{"name":"until","in":"query","required":false,"type":"string"},{"name":"processDefId","in":"query","required":false,"type":"string"},{"name":"instanceId","in":"query","required":false,"type":"string"}]}},"/bpm/api/4.0/tasks/{id}":{"get":{"operationId":"{id}","parameters":[{"name":"expand","in":"query","required":false,"type":"string"},{"name":"metadataFlag","in":"query","required":false,"type":"boolean"},{"name":"id","in":"path","required":true,"type":"string"},{"name":"expand","in":"query","required":false,"type":"string"},{"name":"metadataFlag","in":"query","required":false,"type":"boolean"}]},"put":{"operationId":"{id}","consumes":["application/json"],"parameters":[{"name":"id","in":"path","required":true,"type":"string"},{"in":"body","name":"body","description":"Request body","required":true}]}},"/bpm/api/4.0/tasks/{id}/attachments":{"get":{"operationId":"{id}/attachments","parameters":[{"name":"id","in":"path","required":true,"type":"string"}]},"post":{"operationId":"{id}/attachments","consumes":["multipart/mixed"],"parameters":[{"name":"id","in":"path","required":true,"type":"string"},{"in":"body","name":"body","description":"Request body","required":true}]}},"/bpm/api/4.0/tasks/{id}/attachments/{attachmentName}":{"get":{"operationId":"{id}/attachments/{attachmentName}","parameters":[{"name":"id","in":"path","required":true,"type":"string"},{"name":"attachmentName","in":"path","required":true,"type":"string"}]},"delete":{"operationId":"{id}/attachments/{attachmentName}","parameters":[{"name":"id","in":"path","required":true,"type":"string"},{"name":"attachmentName","in":"path","required":true,"type":"string"}]}},"/bpm/api/4.0/tasks/{id}/attachments/{attachmentName}/stream":{"get":{"operationId":"{id}/attachments/{attachmentName}/stream","parameters":[{"name":"id","in":"path","required":true,"type":"string"},{"name":"attachmentName","in":"path","required":true,"type":"string"}]}},"/bpm/api/4.0/tasks/{id}/comments":{"get":{"operationId":"{id}/comments","parameters":[{"name":"id","in":"path","required":true,"type":"string"}]},"post":{"operationId":"{id}/comments","consumes":["application/json"],"parameters":[{"name":"id","in":"path","required":true,"type":"string"},{"in":"body","name":"body","description":"Request body","required":true}]}},"/bpm/api/4.0/tasks/{id}/conversations":{"get":{"operationId":"{id}/conversations","parameters":[{"name":"name","in":"query","required":false,"type":"string"},{"name":"id","in":"path","required":true,"type":"string"},{"name":"name","in":"query","required":false,"type":"string"}]}},"/bpm/api/4.0/tasks/{id}/conversations/{conversationId}":{"get":{"operationId":"{id}/conversations/{conversationId}","parameters":[{"name":"id","in":"path","required":true,"type":"string"},{"name":"conversationId","in":"path","required":true,"type":"string"}]}},"/bpm/api/4.0/tasks/{id}/folders":{"get":{"operationId":"{id}/folders","parameters":[{"name":"name","in":"query","required":false,"type":"string"},{"name":"id","in":"path","required":true,"type":"string"},{"name":"name","in":"query","required":false,"type":"string"}]}},"/bpm/api/4.0/tasks/{id}/folders/{folderId}":{"get":{"operationId":"{id}/folders/{folderId}","parameters":[{"name":"id","in":"path","required":true,"type":"string"},{"name":"folderId","in":"path","required":true,"type":"string"}]}},"/bpm/api/4.0/tasks/{id}/form":{"get":{"operationId":"{id}/form","parameters":[{"name":"user-agent","in":"header","required":false,"type":"string"},{"name":"readOnly","in":"query","required":false,"type":"string"},{"name":"id","in":"path","required":true,"type":"string"},{"name":"user-agent","in":"header","required":false,"type":"string"},{"name":"readOnly","in":"query","required":false,"type":"string"}]}},"/bpm/api/4.0/tasks/{id}/form/live":{"get":{"operationId":"{id}/form/live","parameters":[{"name":"getURI","in":"query","required":false,"type":"string"},{"name":"id","in":"path","required":true,"type":"string"},{"name":"getURI","in":"query","required":false,"type":"string"}]},"put":{"operationId":"{id}/form/live","consumes":["application/json"],"parameters":[{"name":"Cookie","in":"header","required":false,"type":"string"},{"name":"id","in":"path","required":true,"type":"string"},{"name":"Cookie","in":"header","required":false,"type":"string"},{"in":"body","name":"body","description":"Request body","required":true}]}},"/bpm/api/4.0/tasks/{id}/history":{"get":{"operationId":"{id}/history","parameters":[{"name":"displayStyle","in":"query","required":false,"type":"string"},{"name":"id","in":"path","required":true,"type":"string"},{"name":"displayStyle","in":"query","required":false,"type":"string"}]}},"/bpm/api/4.0/tasks/{id}/payload":{"get":{"operationId":"{id}/payload","parameters":[{"name":"id","in":"path","required":true,"type":"string"}]},"post":{"operationId":"{id}/payload","consumes":["application/json"],"parameters":[{"name":"id","in":"path","required":true,"type":"string"},{"in":"body","name":"body","description":"Request body","required":true}]}},"/bpm/api/4.0/tasks/{id}/todoTasks":{"get":{"operationId":"{id}/todoTasks","parameters":[{"name":"id","in":"path","required":true,"type":"string"}]}},"/bpm/api/4.0/webforms":{},"/bpm/api/4.0/webforms/{formDefId}/executeRest/{restExecutionId}":{"post":{"operationId":"{formDefId}/executeRest/{restExecutionId}","consumes":["application/json","application/xml"],"parameters":[{"name":"formDefId","in":"path","required":true,"type":"string"},{"name":"restExecutionId","in":"path","required":true,"type":"string"},{"in":"body","name":"body","description":"Request body","required":true}]}},"/bpm/api/4.0/webforms/{id}":{"get":{"operationId":"{id}","parameters":[{"name":"id","in":"path","required":true,"type":"string"}]}}}}